{
	"X유니스텔라네온빔": {
		"색상": [
			"yellow",
			"green"
		],
		"분위기": [
			"활발",
			"화려"
		],
		"디자인": [
			"풀컬러",
			"마블",
			"패턴"
		],
		"날씨": [
			"여름"
		]
	},
	"X유니스텔라블랙오닉스": {
		"색상": [
			"black"
		],
		"분위기": [
			"시크"
		],
		"디자인": [
			"풀컬러"
		],
		"날씨": [
			"여름",
			"겨울"
		]
	},
	"X유니스텔라오로라나이트": {
		"색상": [
			"purple"
		],
		"분위기": [
			"활발",
			"화려"
		],
		"디자인": [
			"풀컬러"
		],
		"날씨": [
			"여름",
			"비"
		]
	},
	"X유니스텔라핑크피버": {
		"색상": [
			"pink"
		],
		"분위기": [
			"활발",
			"화려"
		],
		"디자인": [
			"풀컬러"
		],
		"날씨": [
			"여름",
			"맑음"
		]
	},
	"유니스텔라글래시화이트": {
		"색상": [
			"white"
		],
		"분위기": [
			"청순",
			"웨딩"
		],
		"디자인": [
			"풀컬러"
		],
		"날씨": [
			"봄",
			"여름",
			"겨울"
		]
	},
	"유니스텔라핑크글로우": {
		"색상": [
			"pink"
		],
		"분위기": [
			"청순",
			"활발",
			"데일리",
			"큐티"
		],
		"디자인": [
			"풀컬러"
		],
		"날씨": [
			"봄",
			"여름",
			"맑음"
		]
	},
	"페디큐어골든샌드": {
		"색상": [
			"gold"
		],
		"분위기": [
			"화려",
			"웨딩"
		],
		"디자인": [
			"글리터",
			"시스루"
		],
		"날씨": [
			"여름",
			"가을"
		]
	},
	"페디큐어글로우베리": {
		"색상": [
			"red"
		],
		"분위기": [
			"활발",
			"화려",
			"큐티"
		],
		"디자인": [
			"글리터",
			"풀컬러"
		],
		"날씨": [
			"여름",
			"겨울"
		]
	},
	"페디큐어글린트모브페디": {
		"색상": [
			"pink"
		],
		"분위기": [
			"청순",
			"활발",
			"데일리",
			"큐티"
		],
		"디자인": [
			"글리터",
			"풀컬러"
		],
		"날씨": [
			"여름",
			"봄",
			"맑음"
		]
	},
	"페디큐어글리터웨이브": {
		"색상": [
			"purple"
		],
		"분위기": [
			"청순",
			"데일리",
			"큐티"
		],
		"디자인": [
			"글리터",
			"풀컬러"
		],
		"날씨": [
			"여름",
			"봄"
		]
	},
	"페디큐어글린트블루페디": {
		"색상": [
			"black"
		],
		"분위기": [
			"시크",
			"데일리"
		],
		"디자인": [
			"글리터",
			"풀컬러"
		],
		"날씨": [
			"여름",
			"겨울"
		]
	},
	"페디큐어글린트올리브페디": {
		"색상": [
			"yellow"
		],
		"분위기": [
			"청순",
			"활발",
			"데일리",
			"큐티"
		],
		"디자인": [
			"글리터",
			"풀컬러"
		],
		"날씨": [
			"여름",
			"봄",
			"맑음"
		]
	},
	"페디큐어나이트플레이크": {
		"색상": [
			"blue"
		],
		"분위기": [
			"시크",
			"시원"
		],
		"디자인": [
			"글리터",
			"시스루"
		],
		"날씨": [
			"여름",
			"겨울",
			"비"
		]
	},
	"페디큐어다운바이올렛": {
		"색상": [
			"purple"
		],
		"분위기": [
			"청순",
			"데일리"
		],
		"디자인": [
			"풀컬러"
		],
		"날씨": [
			"봄",
			"가을"
		]
	},
	"페디큐어다크나이트": {
		"색상": [
			"black",
			"gold"
		],
		"분위기": [
			"시크",
			"화려"
		],
		"디자인": [
			"글리터"
		],
		"날씨": [
			"가을",
			"겨울",
			"눈"
		]
	},
	"페디큐어다크사파이어": {
		"색상": [
			"blue"
		],
		"분위기": [
			"시크",
			"데일리",
			"시원"
		],
		"디자인": [
			"풀컬러"
		],
		"날씨": [
			"여름",
			"겨울",
			"비"
		]
	},
	"페디큐어대즐링데이지": {
		"색상": [
			"green",
			"silver"
		],
		"분위기": [
			"청순",
			"활발",
			"큐티"
		],
		"디자인": [
			"드로잉"
		],
		"날씨": [
			"봄",
			"여름",
			"맑음"
		]
	},
	"페디큐어대즐링올리브": {
		"색상": [
			"green"
		],
		"분위기": [
			"청순",
			"활발",
			"데일리",
			"큐티"
		],
		"디자인": [
			"자개",
			"풀컬러"
		],
		"날씨": [
			"봄",
			"여름",
			"맑음"
		]
	},
	"페디큐어대즐링퍼플": {
		"색상": [
			"purple",
			"blue",
			"pink"
		],
		"분위기": [
			"활발",
			"화려",
			"시원"
		],
		"디자인": [
			"자개",
			"마블",
			"그라데이션",
			"글리터"
		],
		"날씨": [
			"여름",
			"비"
		]
	},
	"페디큐어데이지데이": {
		"색상": [
			"white",
			"beige"
		],
		"분위기": [
			"청순",
			"데일리"
		],
		"디자인": [
			"풀컬러",
			"자개",
			"시스루"
		],
		"날씨": [
			"봄",
			"여름",
			"맑음"
		]
	},
	"페디큐어드리밍화이트": {
		"색상": [
			"white"
		],
		"분위기": [
			"시크",
			"큐티"
		],
		"디자인": [
			"시스루",
			"패턴",
			"글리터"
		],
		"날씨": [
			"여름",
			"비",
			"눈"
		]
	},
	"페디큐어드림랜드": {
		"색상": [
			"blue",
			"purple",
			"pink"
		],
		"분위기": [
			"청순",
			"데일리",
			"큐티",
			"웨딩",
			"시원"
		],
		"디자인": [
			"마블",
			"그라데이션",
			"글리터"
		],
		"날씨": [
			"봄",
			"여름",
			"겨울",
			"비",
			"눈"
		]
	},
	"페디큐어딥터치": {
		"색상": [
			"blue",
			"purple"
		],
		"분위기": [
			"시크",
			"데일리"
		],
		"디자인": [
			"마블",
			"그라데이션",
			"풀컬러"
		],
		"날씨": [
			"겨울",
			"비",
			"눈"
		]
	},
	"페디큐어라벤더페탈": {
		"색상": [
			"pink",
			"silver",
			"white"
		],
		"분위기": [
			"청순",
			"데일리",
			"화려",
			"큐티"
		],
		"디자인": [
			"자개",
			"글리터"
		],
		"날씨": [
			"봄",
			"여름",
			"눈"
		]
	},
	"페디큐어라이크잇": {
		"색상": [
			"green"
		],
		"분위기": [
			"활발",
			"큐티"
		],
		"디자인": [
			"드로잉",
			"글리터"
		],
		"날씨": [
			"봄",
			"여름",
			"맑음"
		]
	},
	"페디큐어라이트샐먼": {
		"색상": [
			"pink"
		],
		"분위기": [
			"청순",
			"데일리",
			"큐티"
		],
		"디자인": [
			"풀컬러"
		],
		"날씨": [
			"봄",
			"여름",
			"맑음"
		]
	},
	"페디큐어라일락페탈": {
		"색상": [
			"pink",
			"purple"
		],
		"분위기": [
			"청순",
			"데일리",
			"큐티"
		],
		"디자인": [
			"자개",
			"시스루"
		],
		"날씨": [
			"봄",
			"여름",
			"맑음"
		]
	},
	"페디큐어블리오브제": {
		"색상": [
			"pink",
			"blue"
		],
		"분위기": [
			"청순",
			"활발",
			"데일리",
			"큐티"
		],
		"디자인": [
			"자개",
			"풀컬러"
		],
		"날씨": [
			"봄",
			"여름",
			"맑음"
		]
	},
	"페디큐어러블리피크닉": {
		"색상": [
			"red"
		],
		"분위기": [
			"큐티",
			"활발"
		],
		"디자인": [
			"패턴",
			"체크",
			"풀컬러"
		],
		"날씨": [
			"봄",
			"여름",
			"맑음"
		]
	},
	"페디큐어러블리핑크페탈": {
		"색상": [
			"pink"
		],
		"분위기": [
			"큐티",
			"활발",
			"데일리"
		],
		"디자인": [
			"자개",
			"풀컬러"
		],
		"날씨": [
			"봄",
			"여름",
			"맑음"
		]
	},
	"페디큐어레드페탈": {
		"색상": [
			"red"
		],
		"분위기": [
			"활발",
			"화려"
		],
		"디자인": [
			"자개",
			"시스루"
		],
		"날씨": [
			"봄",
			"여름",
			"맑음"
		]
	},
	"페디큐어레인보우크림": {
		"색상": [
			"pink",
			"gold"
		],
		"분위기": [
			"청순",
			"활발",
			"화려",
			"큐티"
		],
		"디자인": [
			"마블",
			"글리터"
		],
		"날씨": [
			"봄",
			"여름",
			"겨울",
			"눈"
		]
	},
	"페디큐어리얼블루": {
		"색상": [
			"blue"
		],
		"분위기": [
			"시크",
			"화려",
			"시원"
		],
		"디자인": [
			"풀컬러"
		],
		"날씨": [
			"여름",
			"겨울",
			"비"
		]
	},
	"페디큐어리프플레이크": {
		"색상": [
			"green"
		],
		"분위기": [
			"활발",
			"시크"
		],
		"디자인": [
			"시스루",
			"글리터"
		],
		"날씨": [
			"여름",
			"비"
		]
	},
	"페디큐어마이레인보우": {
		"색상": [
			"red",
			"blue",
			"orange",
			"yellow"
		],
		"분위기": [
			"활발",
			"화려",
			"큐티"
		],
		"디자인": [
			"드로잉",
			"풀컬러"
		],
		"날씨": [
			"여름",
			"비"
		]
	},
	"페디큐어메이플레인": {
		"색상": [
			"brown",
			"beige"
		],
		"분위기": [
			"청순",
			"데일리"
		],
		"디자인": [
			"마블",
			"그라데이션",
			"시럽"
		],
		"날씨": [
			"가을"
		]
	},
	"페디큐어미드나이트": {
		"색상": [
			"blue",
			"black"
		],
		"분위기": [
			"시크",
			"데일리"
		],
		"디자인": [
			"글리터",
			"풀컬러"
		],
		"날씨": [
			"겨울",
			"눈"
		]
	},
	"페디큐어미라클라벤더": {
		"색상": [
			"pink",
			"purple"
		],
		"분위기": [
			"활발",
			"화려",
			"큐티"
		],
		"디자인": [
			"글리터",
			"자개"
		],
		"날씨": [
			"봄",
			"여름"
		]
	},
	"페디큐어미라클블루": {
		"색상": [
			"blue"
		],
		"분위기": [
			"활발",
			"화려",
			"큐티",
			"시원"
		],
		"디자인": [
			"글리터",
			"자개"
		],
		"날씨": [
			"여름",
			"비"
		]
	},
	"페디큐어미스티나이트": {
		"색상": [
			"gray"
		],
		"분위기": [
			"시크",
			"데일리"
		],
		"디자인": [
			"풀컬러"
		],
		"날씨": [
			"가을",
			"비"
		]
	},
	"페디큐어미스틱데이즈": {
		"색상": [
			"blue"
		],
		"분위기": [
			"화려",
			"시원"
		],
		"디자인": [
			"글리터"
		],
		"날씨": [
			"여름",
			"비"
		]
	},
	"페디큐어미스틱브론즈": {
		"색상": [
			"gold"
		],
		"분위기": [
			"화려"
		],
		"디자인": [
			"글리터"
		],
		"날씨": [
			"가을",
			"겨울"
		]
	},
	"페디큐어미스틱블루": {
		"색상": [
			"blue",
			"purple"
		],
		"분위기": [
			"시크",
			"화려",
			"시원"
		],
		"디자인": [
			"글리터",
			"마블",
			"그라데이션",
			"풀컬러"
		],
		"날씨": [
			"여름",
			"가을",
			"겨울",
			"비"
		]
	},
	"페디큐어미스틱블룸페디": {
		"색상": [
			"gold"
		],
		"분위기": [
			"청순",
			"화려",
			"데일리"
		],
		"디자인": [
			"글리터",
			"풀컬러"
		],
		"날씨": [
			"가을",
			"겨울"
		]
	},
	"페디큐어미스틱실버": {
		"색상": [
			"silver"
		],
		"분위기": [
			"시크",
			"화려",
			"웨딩"
		],
		"디자인": [
			"글리터",
			"풀컬러"
		],
		"날씨": [
			"여름",
			"겨울",
			"눈"
		]
	},
	"페디큐어미스틱핑크": {
		"색상": [
			"pink"
		],
		"분위기": [
			"청순",
			"화려",
			"데일리",
			"웨딩"
		],
		"디자인": [
			"글리터",
			"마블",
			"풀컬러"
		],
		"날씨": [
			"여름",
			"겨울",
			"눈"
		]
	},
	"페디큐어민트베어": {
		"색상": [
			"green"
		],
		"분위기": [
			"청순",
			"활발",
			"데일리",
			"큐티"
		],
		"디자인": [
			"글리터",
			"마블",
			"풀컬러"
		],
		"날씨": [
			"여름",
			"봄"
		]
	},
	"페디큐어베리레드": {
		"색상": [
			"red"
		],
		"분위기": [
			"시크",
			"활발",
			"화려"
		],
		"디자인": [
			"풀컬러"
		],
		"날씨": [
			"여름"
		]
	},
	"페디큐어베이비올리브": {
		"색상": [
			"green"
		],
		"분위기": [
			"청순",
			"데일리"
		],
		"디자인": [
			"풀컬러"
		],
		"날씨": [
			"봄",
			"여름"
		]
	},
	"페디큐어블랙잉크": {
		"색상": [
			"black"
		],
		"분위기": [
			"시크",
			"데일리"
		],
		"디자인": [
			"풀컬러"
		],
		"날씨": [
			"겨울"
		]
	},
	"페디큐어블러싱베어": {
		"색상": [
			"pink"
		],
		"분위기": [
			"청순",
			"데일리",
			"큐티"
		],
		"디자인": [
			"풀컬러",
			"글리터"
		],
		"날씨": [
			"봄",
			"맑음"
		]
	},
	"페디큐어블루도트": {
		"색상": [
			"blue",
			"white"
		],
		"분위기": [
			"청순",
			"데일리",
			"시원"
		],
		"디자인": [
			"풀컬러",
			"패턴"
		],
		"날씨": [
			"여름",
			"비"
		]
	},
	"페디큐어블링선셋": {
		"색상": [
			"orange"
		],
		"분위기": [
			"활발",
			"화려",
			"큐티"
		],
		"디자인": [
			"풀컬러",
			"글리터"
		],
		"날씨": [
			"봄",
			"여름"
		]
	},
	"페디큐어빅플라워": {
		"색상": [
			"yellow",
			"blue"
		],
		"분위기": [
			"활발",
			"큐티"
		],
		"디자인": [
			"드로잉",
			"시스루"
		],
		"날씨": [
			"봄",
			"여름"
		]
	},
	"페디큐어샤이니벨": {
		"색상": [
			"gray",
			"gold"
		],
		"분위기": [
			"시크",
			"데일리"
		],
		"디자인": [
			"글리터",
			"풀컬러"
		],
		"날씨": [
			"가을"
		]
	},
	"페디큐어샤이닝데이": {
		"색상": [
			"white",
			"silver"
		],
		"분위기": [
			"시크",
			"화려",
			"웨딩"
		],
		"디자인": [
			"글리터",
			"자개"
		],
		"날씨": [
			"겨울",
			"눈"
		]
	},
	"페디큐어샤이닝레이크": {
		"색상": [
			"silver"
		],
		"분위기": [
			"화려"
		],
		"디자인": [
			"글리터",
			"자개"
		],
		"날씨": [
			"여름",
			"겨울",
			"눈"
		]
	},
	"페디큐어샤이닝스노우": {
		"색상": [
			"white"
		],
		"분위기": [
			"청순",
			"시크",
			"데일리",
			"화려",
			"웨딩",
			"큐티"
		],
		"디자인": [
			"풀컬러"
		],
		"날씨": [
			"여름",
			"겨울",
			"눈"
		]
	},
	"페디큐어샤이닝오팔": {
		"색상": [
			"white"
		],
		"분위기": [
			"청순",
			"시크",
			"데일리",
			"화려",
			"웨딩",
			"큐티"
		],
		"디자인": [
			"풀컬러"
		],
		"날씨": [
			"여름",
			"겨울",
			"눈"
		]
	},
	"페디큐어샤이닝웨이브페디": {
		"색상": [
			"purple"
		],
		"분위기": [
			"청순",
			"데일리",
			"큐티",
			"시원"
		],
		"디자인": [
			"풀컬러",
			"글리터"
		],
		"날씨": [
			"여름",
			"비"
		]
	},
	"페디큐어샤이닝피오니": {
		"색상": [
			"white",
			"pink"
		],
		"분위기": [
			"청순",
			"큐티"
		],
		"디자인": [
			"풀컬러",
			"글리터"
		],
		"날씨": [
			"눈"
		]
	},
	"페디큐어서퍼블루": {
		"색상": [
			"gray",
			"blue"
		],
		"분위기": [
			"청순",
			"데일리",
			"시원"
		],
		"디자인": [
			"시스루",
			"드로잉"
		],
		"날씨": [
			"여름",
			"겨울",
			"눈",
			"비"
		]
	},
	"페디큐어셉템버윈드": {
		"색상": [
			"white",
			"beige"
		],
		"분위기": [
			"청순",
			"데일리",
			"시크"
		],
		"디자인": [
			"마블",
			"드로잉"
		],
		"날씨": [
			"여름",
			"가을",
			"겨울",
			"눈"
		]
	},
	"페디큐어쉬머링샤베트": {
		"색상": [
			"white",
			"pink"
		],
		"분위기": [
			"청순",
			"활발",
			"화려",
			"큐티"
		],
		"디자인": [
			"자개",
			"마블",
			"그라데이션",
			"글리터"
		],
		"날씨": [
			"여름",
			"겨울",
			"눈"
		]
	},
	"페디큐어스마일체커보드": {
		"색상": [
			"white",
			"black"
		],
		"분위기": [
			"활발",
			"화려",
			"큐티"
		],
		"디자인": [
			"드로잉",
			"체크",
			"패턴",
			"글리터"
		],
		"날씨": [
			"겨울"
		]
	},
	"페디큐어스위밍카푸": {
		"색상": [
			"blue",
			"yellow"
		],
		"분위기": [
			"활발",
			"시원",
			"큐티"
		],
		"디자인": [
			"드로잉",
			"시스루"
		],
		"날씨": [
			"여름",
			"비"
		]
	},
	"페디큐어스위트그린": {
		"색상": [
			"green"
		],
		"분위기": [
			"활발",
			"데일리",
			"큐티"
		],
		"디자인": [
			"글리터"
		],
		"날씨": [
			"봄",
			"여름",
			"맑음"
		]
	},
	"페디큐어스타라이트드롭": {
		"색상": [
			"black",
			"white"
		],
		"분위기": [
			"시크"
		],
		"디자인": [
			"글리터"
		],
		"날씨": [
			"겨울"
		]
	},
	"페디큐어스타페어리": {
		"색상": [
			"white"
		],
		"분위기": [
			"청순",
			"시크",
			"웨딩"
		],
		"디자인": [
			"글리터"
		],
		"날씨": [
			"겨울",
			"눈"
		]
	},
	"페디큐어스테리나이트스카이": {
		"색상": [
			"blue",
			"purple"
		],
		"분위기": [
			"시크",
			"데일리",
			"시원"
		],
		"디자인": [
			"글리터",
			"마블",
			"그라데이션"
		],
		"날씨": [
			"여름",
			"비"
		]
	},
	"페디큐어스테리민트": {
		"색상": [
			"blue"
		],
		"분위기": [
			"청순",
			"데일리",
			"시원"
		],
		"디자인": [
			"글리터",
			"풀컬러"
		],
		"날씨": [
			"여름",
			"비"
		]
	},
	"페디큐어스테리실버": {
		"색상": [
			"silver"
		],
		"분위기": [
			"청순",
			"화려",
			"웨딩"
		],
		"디자인": [
			"글리터",
			"풀컬러"
		],
		"날씨": [
			"겨울",
			"눈"
		]
	},
	"페디큐어스테리핑크": {
		"색상": [
			"pink"
		],
		"분위기": [
			"청순",
			"화려"
		],
		"디자인": [
			"글리터",
			"풀컬러"
		],
		"날씨": [
			"봄"
		]
	},
	"페디큐어스테리화이트": {
		"색상": [
			"white"
		],
		"분위기": [
			"청순",
			"화려",
			"웨딩"
		],
		"디자인": [
			"글리터",
			"풀컬러"
		],
		"날씨": [
			"겨울",
			"눈"
		]
	},
	"페디큐어시크릿리조트": {
		"색상": [
			"blue",
			"silver"
		],
		"분위기": [
			"활발",
			"화려",
			"시원"
		],
		"디자인": [
			"마블",
			"글리터",
			"드로잉"
		],
		"날씨": [
			"여름",
			"비"
		]
	},
	"페디큐어시크릿비치": {
		"색상": [
			"white",
			"gold"
		],
		"분위기": [
			"화려"
		],
		"디자인": [
			"자개",
			"글리터"
		],
		"날씨": [
			"여름"
		]
	},
	"페디큐어실버플레이크": {
		"색상": [
			"gray",
			"silver"
		],
		"분위기": [
			"청순",
			"시크",
			"데일리"
		],
		"디자인": [
			"시스루",
			"글리터"
		],
		"날씨": [
			"겨울",
			"눈"
		]
	},
	"페디큐어심포니": {
		"색상": [
			"gold",
			"white"
		],
		"분위기": [
			"청순",
			"화려",
			"웨딩"
		],
		"디자인": [
			"패턴",
			"글리터"
		],
		"날씨": [
			"겨울",
			"눈"
		]
	},
	"페디큐어썸머블라썸": {
		"색상": [
			"pink",
			"blue"
		],
		"분위기": [
			"활발",
			"큐티"
		],
		"디자인": [
			"풀컬러",
			"글리터"
		],
		"날씨": [
			"봄",
			"여름"
		]
	},
	"페디큐어레이지나이트": {
		"색상": [
			"blue",
			"black"
		],
		"분위기": [
			"시크"
		],
		"디자인": [
			"마블",
			"풀컬러"
		],
		"날씨": [
			"겨울",
			"비",
			"눈"
		]
	},
	"페디큐어아쿠아블루": {
		"색상": [
			"blue"
		],
		"분위기": [
			"활발",
			"데일리",
			"큐티",
			"시원"
		],
		"디자인": [
			"풀컬러"
		],
		"날씨": [
			"여름",
			"비"
		]
	},
	"페디큐어어나더타임": {
		"색상": [
			"purple"
		],
		"분위기": [
			"청순",
			"데일리",
			"큐티"
		],
		"디자인": [
			"마블",
			"그라데이션",
			"풀컬러"
		],
		"날씨": [
			"봄",
			"여름",
			"비"
		]
	},
	"페디큐어언더더오션": {
		"색상": [
			"white",
			"green"
		],
		"분위기": [
			"청순",
			"데일리",
			"큐티"
		],
		"디자인": [
			"마블",
			"그라데이션",
			"풀컬러",
			"자개"
		],
		"날씨": [
			"여름",
			"비"
		]
	},
	"페디큐어오로라듀": {
		"색상": [
			"pink",
			"blue",
			"purple"
		],
		"분위기": [
			"청순",
			"화려",
			"큐티"
		],
		"디자인": [
			"글리터",
			"풀컬러"
		],
		"날씨": [
			"여름",
			"비"
		]
	},
	"페디큐어오션아이즈": {
		"색상": [
			"white",
			"blue"
		],
		"분위기": [
			"활발",
			"청순",
			"시원"
		],
		"디자인": [
			"드로잉",
			"자개"
		],
		"날씨": [
			"여름",
			"비"
		]
	},
	"페디큐어조이풀피크닉": {
		"색상": [
			"blue"
		],
		"분위기": [
			"청순",
			"데일리"
		],
		"디자인": [
			"체크",
			"패턴",
			"풀컬러"
		],
		"날씨": [
			"가을",
			"겨울"
		]
	},
	"페디큐어쥬시레몬페디": {
		"색상": [
			"yellow"
		],
		"분위기": [
			"활발",
			"화려",
			"시원"
		],
		"디자인": [
			"풀컬러"
		],
		"날씨": [
			"여름",
			"비"
		]
	},
	"페디큐어쥬시만다린페디": {
		"색상": [
			"orange"
		],
		"분위기": [
			"활발",
			"화려",
			"시원"
		],
		"디자인": [
			"풀컬러"
		],
		"날씨": [
			"여름"
		]
	},
	"페디큐어쥬시키위페디": {
		"색상": [
			"green"
		],
		"분위기": [
			"활발",
			"화려",
			"시원"
		],
		"디자인": [
			"풀컬러"
		],
		"날씨": [
			"여름",
			"비"
		]
	},
	"페디큐어체리버건디": {
		"색상": [
			"red"
		],
		"분위기": [
			"시크",
			"화려"
		],
		"디자인": [
			"풀컬러"
		],
		"날씨": [
			"여름",
			"가을"
		]
	},
	"페디큐어체크크레용": {
		"색상": [
			"red",
			"yellow"
		],
		"분위기": [
			"활발",
			"화려",
			"큐티"
		],
		"디자인": [
			"시스루"
		],
		"날씨": [
			"여름"
		]
	},
	"페디큐어체크파스텔": {
		"색상": [
			"pink",
			"yellow"
		],
		"분위기": [
			"활발",
			"청순",
			"큐티"
		],
		"디자인": [
			"시스루"
		],
		"날씨": [
			"봄"
		]
	},
	"페디큐어칼라풀스마일": {
		"색상": [
			"purple"
		],
		"분위기": [
			"활발",
			"큐티"
		],
		"디자인": [
			"드로잉"
		],
		"날씨": [
			"봄",
			"여름",
			"맑음"
		]
	},
	"페디큐어코랄판타지": {
		"색상": [
			"pink"
		],
		"분위기": [
			"청순",
			"큐티"
		],
		"디자인": [
			"마블",
			"글리터"
		],
		"날씨": [
			"봄",
			"여름",
			"맑음"
		]
	},
	"페디큐어코지화이트": {
		"색상": [
			"white"
		],
		"분위기": [
			"청순",
			"데일리"
		],
		"디자인": [
			"풀컬러"
		],
		"날씨": [
			"봄",
			"겨울",
			"맑음",
			"눈"
		]
	},
	"페디큐어크리미민트": {
		"색상": [
			"green",
			"blue"
		],
		"분위기": [
			"청순",
			"데일리"
		],
		"디자인": [
			"풀컬러"
		],
		"날씨": [
			"가을",
			"겨울",
			"눈"
		]
	},
	"페디큐어크리미오션": {
		"색상": [
			"blue"
		],
		"분위기": [
			"청순",
			"시원"
		],
		"디자인": [
			"풀컬러",
			"마블"
		],
		"날씨": [
			"여름"
		]
	},
	"페디큐어크리스탈티어스": {
		"색상": [
			"white"
		],
		"분위기": [
			"시크",
			"웨딩"
		],
		"디자인": [
			"풀컬러",
			"글리터"
		],
		"날씨": [
			"여름",
			"겨울",
			"눈"
		]
	},
	"페디큐어클라우드캔디": {
		"색상": [
			"gold"
		],
		"분위기": [
			"화려"
		],
		"디자인": [
			"풀컬러",
			"글리터"
		],
		"날씨": [
			"여름",
			"가을"
		]
	},
	"페디큐어트로피칼트래블": {
		"색상": [
			"purple",
			"white"
		],
		"분위기": [
			"청순",
			"화려"
		],
		"디자인": [
			"풀컬러",
			"글리터",
			"드로잉"
		],
		"날씨": [
			"여름",
			"겨울",
			"눈"
		]
	},
	"페디큐어트로피컬그린": {
		"색상": [
			"green"
		],
		"분위기": [
			"시크"
		],
		"디자인": [
			"풀컬러"
		],
		"날씨": [
			"여름",
			"맑음"
		]
	},
	"페디큐어트로피컬아일랜드": {
		"색상": [
			"green"
		],
		"분위기": [
			"활발",
			"시원"
		],
		"디자인": [
			"드로잉",
			"패턴"
		],
		"날씨": [
			"봄",
			"여름",
			"맑음"
		]
	},
	"페디큐어판타지호라이즌": {
		"색상": [
			"pink"
		],
		"분위기": [
			"활발",
			"큐티"
		],
		"디자인": [
			"그라데이션",
			"풀컬러"
		],
		"날씨": [
			"봄",
			"여름",
			"맑음"
		]
	},
	"페디큐어팝핑토핑": {
		"색상": [
			"blue",
			"orange",
			"green",
			"white"
		],
		"분위기": [
			"활발",
			"큐티"
		],
		"디자인": [
			"풀컬러"
		],
		"날씨": [
			"봄",
			"여름",
			"맑음"
		]
	},
	"페디큐어펄리제이드페디": {
		"색상": [
			"green"
		],
		"분위기": [
			"활발",
			"큐티"
		],
		"디자인": [
			"시럽",
			"풀컬러",
			"글리터"
		],
		"날씨": [
			"봄",
			"여름",
			"맑음"
		]
	},
	"페디큐어펑키펑키": {
		"색상": [
			"blue"
		],
		"분위기": [
			"활발",
			"큐티"
		],
		"디자인": [
			"시스루",
			"드로잉"
		],
		"날씨": [
			"여름",
			"비"
		]
	},
	"페디큐어플라이어웨이": {
		"색상": [
			"pink",
			"white"
		],
		"분위기": [
			"청순",
			"큐티",
			"화려"
		],
		"디자인": [
			"글리터",
			"드로잉"
		],
		"날씨": [
			"겨울",
			"눈"
		]
	},
	"페디큐어플레이그라운드": {
		"색상": [
			"orange"
		],
		"분위기": [
			"큐티",
			"화려"
		],
		"디자인": [
			"글리터",
			"드로잉",
			"풀컬러"
		],
		"날씨": [
			"봄",
			"맑음"
		]
	},
	"페디큐어피크닉무드": {
		"색상": [
			"red",
			"white",
			"yellow",
			"blue"
		],
		"분위기": [
			"시크",
			"큐티"
		],
		"디자인": [
			"풀컬러",
			"패턴",
			"체크"
		],
		"날씨": [
			""
		]
	},
	"페디큐어픽시더스트": {
		"색상": [
			"gold"
		],
		"분위기": [
			"화려"
		],
		"디자인": [
			"글리터"
		],
		"날씨": [
			""
		]
	},
	"페디큐어핑크밤": {
		"색상": [
			"pink"
		],
		"분위기": [
			"청순",
			"화려",
			"큐티"
		],
		"디자인": [
			"시럽",
			"드로잉",
			"글리터"
		],
		"날씨": [
			"봄",
			"맑음"
		]
	},
	"페디큐어핑크선셋": {
		"색상": [
			"pink",
			"purple"
		],
		"분위기": [
			"청순",
			"화려",
			"큐티"
		],
		"디자인": [
			"그라데이션",
			"패턴",
			"글리터"
		],
		"날씨": [
			"봄",
			"맑음"
		]
	},
	"페디큐어핑크플뢰르": {
		"색상": [
			"pink",
			"beige"
		],
		"분위기": [
			"청순",
			"큐티"
		],
		"디자인": [
			"자개",
			"풀컬러"
		],
		"날씨": [
			"봄",
			"맑음"
		]
	},
	"페디큐어하하하": {
		"색상": [
			"black"
		],
		"분위기": [
			"시크",
			"큐티"
		],
		"디자인": [
			"시스루",
			"드로잉"
		],
		"날씨": [
			""
		]
	},
	"페디큐어해피스마일": {
		"색상": [
			"yellow",
			"blue"
		],
		"분위기": [
			"활발",
			"큐티"
		],
		"디자인": [
			"패턴",
			"체크",
			"드로잉"
		],
		"날씨": [
			"맑음"
		]
	},
	"페디큐어화이트스텔라": {
		"색상": [
			"white"
		],
		"분위기": [
			"청순",
			"웨딩"
		],
		"디자인": [
			"풀컬러",
			"글리터"
		],
		"날씨": [
			"겨울",
			"눈"
		]
	},
	"페디큐어화이트크러쉬": {
		"색상": [
			"white"
		],
		"분위기": [
			"청순",
			"웨딩"
		],
		"디자인": [
			"시스루",
			"글리터"
		],
		"날씨": [
			"겨울",
			"눈"
		]
	},
	"페디큐어세일링보트": {
		"색상": [
			"blue"
		],
		"분위기": [
			"청순",
			"시원"
		],
		"디자인": [
			"시스루",
			"드로잉"
		],
		"날씨": [
			"여름",
			"비"
		]
	},
	"페디큐어퓨어스마일": {
		"색상": [
			"white",
			"silver"
		],
		"분위기": [
			"화려",
			"활발",
			"큐티"
		],
		"디자인": [
			"글리커",
			"드로잉"
		],
		"날씨": [
			""
		]
	},
	"[01.20 - 02.18] 물병자리 윈터 우라노스": {
		"색상": [
			"blue"
		],
		"분위기": [
			"데일리",
			"시원"
		],
		"디자인": [
			"풀컬러"
		],
		"날씨": [
			"여름",
			"비"
		]
	},
	"[02.19 - 03.20] 물고기자리 스프링 넵튠": {
		"색상": [
			"blue"
		],
		"분위기": [
			"데일리",
			"시원"
		],
		"디자인": [
			"풀컬러"
		],
		"날씨": [
			"여름",
			"비"
		]
	},
	"[03.21 - 04.19] 양자리 스프링 마스": {
		"색상": [
			"red",
			"pink"
		],
		"분위기": [
			"데일리",
			"청순"
		],
		"디자인": [
			"풀컬러"
		],
		"날씨": [
			"봄",
			"가을",
			"맑음"
		]
	},
	"[04.20 - 05.20] 황소자리 썸머 비너스": {
		"색상": [
			"orange"
		],
		"분위기": [
			"데일리",
			"청순"
		],
		"디자인": [
			"풀컬러"
		],
		"날씨": [
			"가을",
			"맑음"
		]
	},
	"[05.21 - 06.21] 쌍둥이자리 썸머 머큐리": {
		"색상": [
			"white"
		],
		"분위기": [
			"데일리",
			"청순"
		],
		"디자인": [
			"풀컬러"
		],
		"날씨": [
			"겨울",
			"눈"
		]
	},
	"[06.22 - 07.22] 게자리 썸머 문": {
		"색상": [
			"gray"
		],
		"분위기": [
			"데일리",
			"시크"
		],
		"디자인": [
			"풀컬러"
		],
		"날씨": [
			"겨울"
		]
	},
	"[07.23 - 08.22] 사자자리 썸머 썬": {
		"색상": [
			"red"
		],
		"분위기": [
			"데일리"
		],
		"디자인": [
			"풀컬러"
		],
		"날씨": [
			"가을"
		]
	},
	"[08.23 - 09.22] 처녀자리 어텀 머큐리": {
		"색상": [
			"white"
		],
		"분위기": [
			"데일리"
		],
		"디자인": [
			"풀컬러"
		],
		"날씨": [
			"겨울",
			"눈"
		]
	},
	"[09.23 - 10.23] 천칭자리 어텀 비너스": {
		"색상": [
			"red",
			"brown"
		],
		"분위기": [
			"데일리",
			"시크"
		],
		"디자인": [
			"풀컬러"
		],
		"날씨": [
			"가을"
		]
	},
	"[10.24 - 11.22] 전갈자리 윈터 플루토": {
		"색상": [
			"blue"
		],
		"분위기": [
			"데일리"
		],
		"디자인": [
			"풀컬러"
		],
		"날씨": [
			"여름"
		]
	},
	"[11.23 - 12.21] 사수자리 윈터 주피터": {
		"색상": [
			"pink"
		],
		"분위기": [
			"데일리",
			"청순"
		],
		"디자인": [
			"풀컬러"
		],
		"날씨": [
			"봄",
			"가을",
			"맑음"
		]
	},
	"[12.22 - 01.19] 염소자리 윈터 새턴": {
		"색상": [
			"green",
			"brown"
		],
		"분위기": [
			"데일리"
		],
		"디자인": [
			"풀컬러"
		],
		"날씨": [
			"겨울"
		]
	},
	"P 곰돌이 오렌지 체크 페디": {
		"색상": [
			"white",
			"yellow",
			"orange"
		],
		"분위기": [
			"데일리",
			"큐티"
		],
		"디자인": [
			"패턴",
			"시스루"
		],
		"날씨": [
			"봄",
			"맑음"
		]
	},
	"P 곰돌이 캬라멜 페디": {
		"색상": [
			"brown"
		],
		"분위기": [
			"데일리",
			"큐티"
		],
		"디자인": [
			"패턴",
			"시스루",
			"풀컬러"
		],
		"날씨": [
			"가을",
			"맑음"
		]
	},
	"P 그루비 페디": {
		"색상": [
			"blue",
			"pink"
		],
		"분위기": [
			"데일리",
			"활발"
		],
		"디자인": [
			"그라데이션",
			"풀컬러"
		],
		"날씨": [
			"여름",
			"비"
		]
	},
	"P 그린 올리브 페디": {
		"색상": [
			"green"
		],
		"분위기": [
			"시크"
		],
		"디자인": [
			"풀컬러"
		],
		"날씨": [
			"가을"
		]
	},
	"P 끌라로 페디": {
		"색상": [
			"white"
		],
		"분위기": [
			"화려",
			"웨딩"
		],
		"디자인": [
			"풀컬러"
		],
		"날씨": [
			"겨울",
			"맑음"
		]
	},
	"P 나전칠기 페디": {
		"색상": [
			"black"
		],
		"분위기": [
			"화려",
			"시크"
		],
		"디자인": [
			"시스루",
			"드로잉"
		],
		"날씨": [
			"겨울",
			"맑음"
		]
	},
	"P 네버랜드 페디": {
		"색상": [
			"pink"
		],
		"분위기": [
			"화려",
			"활발"
		],
		"디자인": [
			"글리터",
			"마블"
		],
		"날씨": [
			"봄",
			"맑음"
		]
	},
	"P 네온 라이트 페디": {
		"색상": [
			"silver",
			"gray",
			"yellow"
		],
		"분위기": [
			"화려",
			"활발"
		],
		"디자인": [
			"글리터",
			"풀컬러"
		],
		"날씨": [
			"겨울",
			"맑음"
		]
	},
	"P 네온 라임 페디": {
		"색상": [
			"yellow",
			"green"
		],
		"분위기": [
			"데일리",
			"활발"
		],
		"디자인": [
			"풀컬러"
		],
		"날씨": [
			"봄",
			"맑음"
		]
	},
	"P 노마드 페디": {
		"색상": [
			"white",
			"green"
		],
		"분위기": [
			"데일리"
		],
		"디자인": [
			"패턴",
			"드로잉",
			"풀컬러"
		],
		"날씨": [
			"여름",
			"맑음"
		]
	},
	"P 뉴 문 페디": {
		"색상": [
			"purple",
			"black"
		],
		"분위기": [
			"데일리",
			"시크"
		],
		"디자인": [
			"마블",
			"시스루",
			"글리터"
		],
		"날씨": [
			"맑음"
		]
	},
	"P 뉴트로 1호 페디": {
		"색상": [
			"white",
			"pink"
		],
		"분위기": [
			"화려",
			"활발"
		],
		"디자인": [
			"시스루",
			"글리터"
		],
		"날씨": [
			"맑음"
		]
	},
	"P 다비 페디": {
		"색상": [
			"white",
			"blue",
			"red"
		],
		"분위기": [
			"데일리",
			"활발"
		],
		"디자인": [
			"풀컬러"
		],
		"날씨": [
			"여름",
			"맑음"
		]
	},
	"P 달링 페디": {
		"색상": [
			"blue",
			"pink"
		],
		"분위기": [
			"데일리",
			"활발",
			"큐티"
		],
		"디자인": [
			"풀컬러",
			"드로잉"
		],
		"날씨": [
			"봄",
			"여름",
			"가을맑음"
		]
	},
	"P 더블 체크 페디": {
		"색상": [
			"pink",
			"yellow"
		],
		"분위기": [
			"큐티",
			"활발"
		],
		"디자인": [
			"풀컬러",
			"드로잉"
		],
		"날씨": [
			"가을맑음"
		]
	},
	"P 데스페라도 페디": {
		"색상": [
			"white",
			"black"
		],
		"분위기": [
			"시크"
		],
		"디자인": [
			"풀컬러"
		],
		"날씨": [
			"여름"
		]
	},
	"P 드림라이크 페디": {
		"색상": [
			"white",
			"pink"
		],
		"분위기": [
			"청순",
			"큐티"
		],
		"디자인": [
			"풀컬러",
			"그라데이션"
		],
		"날씨": [
			"봄",
			"여름",
			"맑음"
		]
	},
	"P 라군 페디": {
		"색상": [
			"blue",
			"gray"
		],
		"분위기": [
			"시크"
		],
		"디자인": [
			"풀컬러"
		],
		"날씨": [
			"여름"
		]
	},
	"P 라벤더 포그 페디": {
		"색상": [
			"blue",
			"pink",
			"white"
		],
		"분위기": [
			"큐티",
			"활발",
			"화려"
		],
		"디자인": [
			"마블"
		],
		"날씨": [
			"봄"
		]
	},
	"P 라붐 페디": {
		"색상": [
			"pink",
			"orange"
		],
		"분위기": [
			"큐티",
			"화려"
		],
		"디자인": [
			"풀컬러"
		],
		"날씨": [
			"가을",
			"맑음"
		]
	},
	"P 라임 주스 페디": {
		"색상": [
			"pink",
			"green"
		],
		"분위기": [
			"큐티"
		],
		"디자인": [
			"드로잉",
			"풀컬러"
		],
		"날씨": [
			"봄",
			"맑음"
		]
	},
	"P 라임에이드 페디": {
		"색상": [
			"green",
			"yellow"
		],
		"분위기": [
			"활발",
			"큐티",
			"데일리"
		],
		"디자인": [
			"글리터",
			"그라데이션",
			"풀컬러"
		],
		"날씨": [
			"봄",
			"여름",
			"맑음"
		]
	},
	"P 랑데뷰 페디": {
		"색상": [
			"blue",
			"white"
		],
		"분위기": [
			"활발",
			"시원"
		],
		"디자인": [
			"드로잉",
			"풀컬러"
		],
		"날씨": [
			"여름"
		]
	},
	"P 레이나 페디": {
		"색상": [
			"red"
		],
		"분위기": [
			"시크",
			"데일리"
		],
		"디자인": [
			"드로잉",
			"시럽",
			"풀컬러"
		],
		"날씨": [
			"겨울",
			"맑음"
		]
	},
	"P 레인보우 페디": {
		"색상": [
			"white",
			"yellow",
			"red",
			"green"
		],
		"분위기": [
			"활발",
			"큐티"
		],
		"디자인": [
			"드로잉",
			"풀컬러"
		],
		"날씨": [
			"봄",
			"여름",
			"가을"
		]
	},
	"P 로맨티크 페디": {
		"색상": [
			"pink"
		],
		"분위기": [
			"데일리",
			"큐티"
		],
		"디자인": [
			"매트",
			"풀컬러"
		],
		"날씨": [
			"봄",
			"맑음"
		]
	},
	"P 로미오 페디": {
		"색상": [
			"red"
		],
		"분위기": [
			"데일리"
		],
		"디자인": [
			"풀컬러"
		],
		"날씨": [
			"가을",
			"맑음"
		]
	},
	"P 롤리 스트라이프 페디": {
		"색상": [
			"blue",
			"white",
			"green"
		],
		"분위기": [
			"데일리",
			"시원",
			"활발"
		],
		"디자인": [
			"드로잉",
			"풀컬러"
		],
		"날씨": [
			"여름",
			"맑음"
		]
	},
	"P 리베라 페디": {
		"색상": [
			"brown",
			"beige",
			"white"
		],
		"분위기": [
			"시크",
			"화려"
		],
		"디자인": [
			"드로잉",
			"풀컬러"
		],
		"날씨": [
			"여름"
		]
	},
	"P 리프 페디": {
		"색상": [
			"pink",
			"green"
		],
		"분위기": [
			"큐티",
			"데일리"
		],
		"디자인": [
			"그라데이션",
			"풀컬러"
		],
		"날씨": [
			"봄"
		]
	},
	"P 리플레이 페디": {
		"색상": [
			"yellow",
			"blue"
		],
		"분위기": [
			"큐티",
			"시원"
		],
		"디자인": [
			"드로잉",
			"풀컬러"
		],
		"날씨": [
			"여름",
			"맑음"
		]
	},
	"P 마블 소다 페디": {
		"색상": [
			"white",
			"blue"
		],
		"분위기": [
			"데일리",
			"시원"
		],
		"디자인": [
			"마블",
			"풀컬러"
		],
		"날씨": [
			"겨울",
			"맑음"
		]
	},
	"P 마스 페디": {
		"색상": [
			"white",
			"pink"
		],
		"분위기": [
			"큐티",
			"화려"
		],
		"디자인": [
			"마블",
			"글리터",
			"그라데이션",
			"시럽"
		],
		"날씨": [
			"봄"
		]
	},
	"P 마이 튤립 페디": {
		"색상": [
			"white",
			"red"
		],
		"분위기": [
			"큐티",
			"데일리",
			"활발"
		],
		"디자인": [
			"드로잉",
			"풀컬러"
		],
		"날씨": [
			"여름",
			"가을",
			"맑음"
		]
	},
	"P 망고 페디": {
		"색상": [
			"yellow"
		],
		"분위기": [
			"활발",
			"큐티"
		],
		"디자인": [
			"풀컬러"
		],
		"날씨": [
			"봄",
			"여름",
			"맑음"
		]
	},
	"P 메르 페디": {
		"색상": [
			"white",
			"blue"
		],
		"분위기": [
			"시원",
			"데일리",
			"활발"
		],
		"디자인": [
			"마블",
			"시럽"
		],
		"날씨": [
			"여름",
			"맑음"
		]
	},
	"P 메리엘 페디": {
		"색상": [
			"white",
			"blue",
			"purple"
		],
		"분위기": [
			"화려"
		],
		"디자인": [
			"마블",
			"글리터"
		],
		"날씨": [
			"겨울"
		]
	},
	"P 메이플 페디": {
		"색상": [
			"red",
			"orange",
			"brown"
		],
		"분위기": [
			"시크"
		],
		"디자인": [
			"풀컬러"
		],
		"날씨": [
			"가을"
		]
	},
	"P 모노 테라조 페디": {
		"색상": [
			"white",
			"pink"
		],
		"분위기": [
			"데일리",
			"큐티"
		],
		"디자인": [
			"드로잉",
			"풀컬러"
		],
		"날씨": [
			"봄",
			"맑음"
		]
	},
	"P 모브블랑 페디": {
		"색상": [
			"red"
		],
		"분위기": [
			"화려",
			"시크"
		],
		"디자인": [
			"시스루",
			"글리터",
			"풀컬러"
		],
		"날씨": [
			"가을"
		]
	},
	"P 몬스테라 페디": {
		"색상": [
			"white",
			"green"
		],
		"분위기": [
			"데일리"
		],
		"디자인": [
			"시스루",
			"시럽",
			"드로잉"
		],
		"날씨": [
			"겨울",
			"눈"
		]
	},
	"P 무어스 페디": {
		"색상": [
			"white",
			"green"
		],
		"분위기": [
			"화려"
		],
		"디자인": [
			"드로잉",
			"풀컬러",
			"시스루"
		],
		"날씨": [
			"겨울",
			"눈"
		]
	},
	"P 문보우 페디": {
		"색상": [
			"pink",
			"purple"
		],
		"분위기": [
			"데일리",
			"큐티"
		],
		"디자인": [
			"그라데이션"
		],
		"날씨": [
			"봄",
			"가을",
			"맑음"
		]
	},
	"P 미뉴에트 페디": {
		"색상": [
			"pink",
			"yellow"
		],
		"분위기": [
			"데일리",
			"활발"
		],
		"디자인": [
			"풀컬러"
		],
		"날씨": [
			"여름",
			"맑음"
		]
	},
	"P 민티 페디": {
		"색상": [
			"green"
		],
		"분위기": [
			"화려"
		],
		"디자인": [
			"드로잉",
			"시스루",
			"풀컬러"
		],
		"날씨": [
			"여름",
			"맑음"
		]
	},
	"P 발레리나 페디": {
		"색상": [
			"pink"
		],
		"분위기": [
			"데일리",
			"청순",
			"큐티"
		],
		"디자인": [
			"매트"
		],
		"날씨": [
			"봄",
			"맑음"
		]
	},
	"P 버블리 페디": {
		"색상": [
			"red",
			"green"
		],
		"분위기": [
			"데일리"
		],
		"디자인": [
			"풀컬러"
		],
		"날씨": [
			"겨울",
			"맑음"
		]
	},
	"P 베르메이 페디": {
		"색상": [
			"red"
		],
		"분위기": [
			"화려"
		],
		"디자인": [
			"글리터"
		],
		"날씨": [
			"가을",
			"맑음"
		]
	},
	"P 베르사 페디": {
		"색상": [
			"white",
			"red"
		],
		"분위기": [
			"화려"
		],
		"디자인": [
			"드로잉",
			"시럽"
		],
		"날씨": [
			"겨울"
		]
	},
	"P 베리 페디": {
		"색상": [
			"pink"
		],
		"분위기": [
			"큐티"
		],
		"디자인": [
			"풀컬러",
			"글리터"
		],
		"날씨": [
			"봄"
		]
	},
	"P 베수비오 페디": {
		"색상": [
			"orange",
			"gray"
		],
		"분위기": [
			"시크"
		],
		"디자인": [
			"시럽",
			"풀컬러"
		],
		"날씨": [
			"겨울"
		]
	},
	"P 베이직 무드 페디": {
		"색상": [
			"pink"
		],
		"분위기": [
			"큐티",
			"데일리"
		],
		"디자인": [
			"시럽",
			"그라데이션"
		],
		"날씨": [
			"봄",
			"가을",
			"맑음"
		]
	},
	"P 베이직페디 1호": {
		"색상": [
			"beige"
		],
		"분위기": [
			"화려",
			"시크"
		],
		"디자인": [
			"시스루",
			"글리터"
		],
		"날씨": [
			"겨울",
			"맑음"
		]
	},
	"P 베이직페디 2호": {
		"색상": [
			"black"
		],
		"분위기": [
			"시크"
		],
		"디자인": [
			"풀컬러"
		],
		"날씨": [
			"겨울"
		]
	},
	"P 베이직페디 3호": {
		"색상": [
			"white"
		],
		"분위기": [
			"청순"
		],
		"디자인": [
			"풀컬러"
		],
		"날씨": [
			"겨울",
			"눈"
		]
	},
	"P 베이직페디 4호": {
		"색상": [
			"red"
		],
		"분위기": [
			"시크"
		],
		"디자인": [
			"풀컬러"
		],
		"날씨": [
			"겨울"
		]
	},
	"P 베케이션 페디": {
		"색상": [
			"orange",
			"blue"
		],
		"분위기": [
			"큐티"
		],
		"디자인": [
			"풀컬러"
		],
		"날씨": [
			"가을"
		]
	},
	"P 별빛 페디": {
		"색상": [
			"black"
		],
		"분위기": [
			"시크"
		],
		"디자인": [
			"풀컬러",
			"글리터"
		],
		"날씨": [
			"겨을"
		]
	},
	"P 뷰 페디": {
		"색상": [
			"white",
			"purple"
		],
		"분위기": [
			"화려",
			"활발"
		],
		"디자인": [
			"마블",
			"자개"
		],
		"날씨": [
			"겨을"
		]
	},
	"P 브라이트 페디": {
		"색상": [
			"beige"
		],
		"분위기": [
			"화려",
			"웨딩"
		],
		"디자인": [
			"드로잉",
			"풀컬러"
		],
		"날씨": [
			"겨을",
			"맑음"
		]
	},
	"P 브로치 페디": {
		"색상": [
			"white",
			"black"
		],
		"분위기": [
			"화려",
			"시크"
		],
		"디자인": [
			"글리터",
			"풀컬러"
		],
		"날씨": [
			"겨을"
		]
	},
	"P 브론즈타임 페디": {
		"색상": [
			"red"
		],
		"분위기": [
			"화려",
			"시크"
		],
		"디자인": [
			"풀컬러",
			"글리터"
		],
		"날씨": [
			"여름",
			"겨을"
		]
	},
	"P 블랙홀 페디": {
		"색상": [
			"black"
		],
		"분위기": [
			"시크"
		],
		"디자인": [
			"매트",
			"풀컬러"
		],
		"날씨": [
			"여름",
			"겨을"
		]
	},
	"P 블러 페디": {
		"색상": [
			"blue"
		],
		"분위기": [
			"활발",
			"시원"
		],
		"디자인": [
			"매트"
		],
		"날씨": [
			"여름",
			"비"
		]
	},
	"P 블레이즈 페디": {
		"색상": [
			"red"
		],
		"분위기": [
			"시크"
		],
		"디자인": [
			"풀컬러"
		],
		"날씨": [
			"봄",
			"가을",
			"맑음"
		]
	},
	"P 블루 드롭 페디": {
		"색상": [
			"white",
			"blue"
		],
		"분위기": [
			"화려",
			"시크",
			"시원"
		],
		"디자인": [
			"풀컬러"
		],
		"날씨": [
			"여름",
			"맑음"
		]
	},
	"P 블루 레이크 페디": {
		"색상": [
			"white"
		],
		"분위기": [
			"청순",
			"웨딩"
		],
		"디자인": [
			"풀컬러"
		],
		"날씨": [
			"겨울",
			"눈"
		]
	},
	"P 블루 문 페디": {
		"색상": [
			"gold",
			"blue"
		],
		"분위기": [
			"시원",
			"시크"
		],
		"디자인": [
			"시스루",
			"드로잉",
			"풀컬러"
		],
		"날씨": [
			"겨울"
		]
	},
	"P 블루 샤크 페디": {
		"색상": [
			"purple",
			"blue"
		],
		"분위기": [
			"시원",
			"화려"
		],
		"디자인": [
			"매트",
			"그라데이션"
		],
		"날씨": [
			"여름"
		]
	},
	"P 블루 워터 페디": {
		"색상": [
			"blue"
		],
		"분위기": [
			"시원",
			"데일리"
		],
		"디자인": [
			"마블",
			"풀컬러"
		],
		"날씨": [
			"여름",
			"맑음"
		]
	},
	"P 블루 홀 페디": {
		"색상": [
			"pink",
			"blue"
		],
		"분위기": [
			"시원",
			"데일리"
		],
		"디자인": [
			"드로잉",
			"풀컬러"
		],
		"날씨": [
			"여름",
			"맑음"
		]
	},
	"P 블루베리 팝 페디": {
		"색상": [
			"purple"
		],
		"분위기": [
			"화려",
			"활발"
		],
		"디자인": [
			"글리터"
		],
		"날씨": [
			"봄",
			"맑음"
		]
	},
	"P 블루팝스 페디": {
		"색상": [
			"blue"
		],
		"분위기": [
			"화려",
			"시원"
		],
		"디자인": [
			"글리터",
			"드로잉",
			"시럽",
			"매트"
		],
		"날씨": [
			"여름",
			"비"
		]
	},
	"P 비 마이 레이디 페디": {
		"색상": [
			"pink"
		],
		"분위기": [
			"큐티",
			"화려"
		],
		"디자인": [
			"자개",
			"풀컬러"
		],
		"날씨": [
			"봄"
		]
	},
	"P 비치 다이빙 페디": {
		"색상": [
			"white",
			"blue"
		],
		"분위기": [
			"시원",
			"화려"
		],
		"디자인": [
			"자개",
			"그라데이션",
			"글리터"
		],
		"날씨": [
			"여름"
		]
	},
	"P 비포 선셋 페디": {
		"색상": [
			"white",
			"orange",
			"blue"
		],
		"분위기": [
			"큐티",
			"데일리"
		],
		"디자인": [
			"자개",
			"그라데이션",
			"풀컬러"
		],
		"날씨": [
			"여름"
		]
	},
	"P 빅 스마일 페디": {
		"색상": [
			"yellow",
			"black"
		],
		"분위기": [
			"큐티",
			"활발"
		],
		"디자인": [
			"드로잉",
			"글리터",
			"풀컬러"
		],
		"날씨": [
			"봄",
			"여름",
			"가을"
		]
	},
	"P 빈티지우드 페디": {
		"색상": [
			"brown"
		],
		"분위기": [
			"화려"
		],
		"디자인": [
			"자개",
			"풀컬러"
		],
		"날씨": [
			"봄",
			"가을"
		]
	},
	"P 새틴 마젠타 페디": {
		"색상": [
			"red"
		],
		"분위기": [
			"화려"
		],
		"디자인": [
			"자개",
			"시럽"
		],
		"날씨": [
			"봄",
			"가을"
		]
	},
	"P 서핑 페디": {
		"색상": [
			"blue",
			"purple",
			"white"
		],
		"분위기": [
			"시원"
		],
		"디자인": [
			"드로잉",
			"그라데이션",
			"풀컬러"
		],
		"날씨": [
			"여름",
			"맑음"
		]
	},
	"P 셀러브리티 페디": {
		"색상": [
			"pink",
			"purple",
			"white"
		],
		"분위기": [
			"화려"
		],
		"디자인": [
			"마블"
		],
		"날씨": [
			"봄",
			"여름",
			"맑음"
		]
	},
	"P 소다 블루 페디": {
		"색상": [
			"blue"
		],
		"분위기": [
			"화려"
		],
		"디자인": [
			"글리터"
		],
		"날씨": [
			"여름"
		]
	},
	"P 슈가 페디": {
		"색상": [
			"white"
		],
		"분위기": [
			"화려",
			"웨딩"
		],
		"디자인": [
			"글리터"
		],
		"날씨": [
			"겨울",
			"눈"
		]
	},
	"P 스위트 페디": {
		"색상": [
			"pink",
			"purple",
			"yellow",
			"blue",
			"green"
		],
		"분위기": [
			"활발"
		],
		"디자인": [
			"풀컬러"
		],
		"날씨": [
			"봄"
		]
	},
	"P 스윗 드림 페디": {
		"색상": [
			"pink",
			"purple"
		],
		"분위기": [
			"큐티",
			"데일리"
		],
		"디자인": [
			"그라데이션",
			"풀컬러"
		],
		"날씨": [
			"봄",
			"가을"
		]
	},
	"P 스타릿 페디": {
		"색상": [
			"white",
			"silver"
		],
		"분위기": [
			"화려"
		],
		"디자인": [
			"시스루",
			"글리터"
		],
		"날씨": [
			"겨울"
		]
	},
	"P 스태리나잇 페디": {
		"색상": [
			"blue",
			"silver"
		],
		"분위기": [
			"화려"
		],
		"디자인": [
			"풀컬러",
			"글리터"
		],
		"날씨": [
			"여름",
			"맑음"
		]
	},
	"P 스터닝 페디": {
		"색상": [
			"green"
		],
		"분위기": [
			"화려"
		],
		"디자인": [
			"시스루",
			"자개",
			"풀컬러"
		],
		"날씨": [
			"여름",
			"맑음"
		]
	},
	"P 스테디페디 1호": {
		"색상": [
			"gold",
			"blue",
			"gray"
		],
		"분위기": [
			"화려"
		],
		"디자인": [
			"자개",
			"드로잉"
		],
		"날씨": [
			"겨울"
		]
	},
	"P 스테디페디 3호": {
		"색상": [
			"pink",
			"beige"
		],
		"분위기": [
			"화려"
		],
		"디자인": [
			"자개",
			"풀컬러"
		],
		"날씨": [
			"겨울"
		]
	},
	"P 스테디페디 5호": {
		"색상": [
			"white",
			"blue"
		],
		"분위기": [
			"화려",
			"웨딩"
		],
		"디자인": [
			"자개",
			"풀컬러"
		],
		"날씨": [
			"겨울"
		]
	},
	"P 스텔라 페디": {
		"색상": [
			"white",
			"purple"
		],
		"분위기": [
			"큐티",
			"데일리"
		],
		"디자인": [
			"드로잉",
			"풀컬러"
		],
		"날씨": [
			"겨울",
			"맑음"
		]
	},
	"P 스파클 페디": {
		"색상": [
			"blue"
		],
		"분위기": [
			"시원",
			"활발",
			"데일리"
		],
		"디자인": [
			"드로잉",
			"풀컬러"
		],
		"날씨": [
			"여름",
			"비"
		]
	},
	"P 스팟라이트 페디": {
		"색상": [
			"blue"
		],
		"분위기": [
			"시원",
			"활발"
		],
		"디자인": [
			"글리터",
			"풀컬러"
		],
		"날씨": [
			"여름",
			"비"
		]
	},
	"P 써머 나잇 페디": {
		"색상": [
			"black"
		],
		"분위기": [
			"시원",
			"화려"
		],
		"디자인": [
			"그라데이션",
			"글리터"
		],
		"날씨": [
			"여름"
		]
	},
	"P 써머 드라이브 페디": {
		"색상": [
			"brown",
			"blue"
		],
		"분위기": [
			"시원",
			"데일리"
		],
		"디자인": [
			"시럽",
			"풀컬러"
		],
		"날씨": [
			"여름"
		]
	},
	"P 썬 데이지 페디": {
		"색상": [
			"yellow"
		],
		"분위기": [
			"큐트",
			"데일리"
		],
		"디자인": [
			"드로잉",
			"풀컬러"
		],
		"날씨": [
			"봄",
			"가을",
			"맑음"
		]
	},
	"P 씨엘로 페디": {
		"색상": [
			"blue"
		],
		"분위기": [
			"활발",
			"시원"
		],
		"디자인": [
			"풀컬러"
		],
		"날씨": [
			"여름",
			"맑음",
			"비"
		]
	},
	"P 아르망 페디": {
		"색상": [
			"red"
		],
		"분위기": [
			"데일리",
			"청순"
		],
		"디자인": [
			"마블",
			"풀컬러"
		],
		"날씨": [
			"봄",
			"맑음"
		]
	},
	"P 아스트로 페디": {
		"색상": [
			"blue"
		],
		"분위기": [
			"화려"
		],
		"디자인": [
			"드로잉",
			"글리터",
			"풀컬러"
		],
		"날씨": [
			"여름",
			"맑음"
		]
	},
	"P 아우라 페디": {
		"색상": [
			"beige",
			"white"
		],
		"분위기": [
			"화려",
			"웨딩"
		],
		"디자인": [
			"시스루",
			"글리터"
		],
		"날씨": [
			"맑음"
		]
	},
	"P 아이스 민트 페디": {
		"색상": [
			"white",
			"green"
		],
		"분위기": [
			"화려"
		],
		"디자인": [
			"시스루",
			"글리터",
			"풀컬러"
		],
		"날씨": [
			"맑음"
		]
	},
	"P 아이시 페디": {
		"색상": [
			"blue",
			"purple"
		],
		"분위기": [
			"화려",
			"시원"
		],
		"디자인": [
			"그라데이션",
			"글리터",
			"풀컬러"
		],
		"날씨": [
			"여름"
		]
	},
	"P 아임 파인 페디": {
		"색상": [
			"blue"
		],
		"분위기": [
			"큐티",
			"활발",
			"시원"
		],
		"디자인": [
			"드로잉",
			"풀컬러"
		],
		"날씨": [
			"여름"
		]
	},
	"P 아주르 페디": {
		"색상": [
			"white",
			"green"
		],
		"분위기": [
			"화려",
			"시원"
		],
		"디자인": [
			"드로잉",
			"글리터",
			"풀컬러"
		],
		"날씨": [
			"여름",
			"맑음"
		]
	},
	"P 아쿠아마린 페디": {
		"색상": [
			"gray"
		],
		"분위기": [
			"화려"
		],
		"디자인": [
			"글리터"
		],
		"날씨": [
			"겨울"
		]
	},
	"P 아틀란티스 페디": {
		"색상": [
			"green",
			"white"
		],
		"분위기": [
			"화려",
			"시원"
		],
		"디자인": [
			"글리터",
			"시스루",
			"풀컬러"
		],
		"날씨": [
			"여름",
			"맑음"
		]
	},
	"P 알로나 비치 페디": {
		"색상": [
			"beige",
			"white",
			"purple",
			"pink"
		],
		"분위기": [
			"큐티"
		],
		"디자인": [
			"드로잉",
			"풀컬러"
		],
		"날씨": [
			"여름",
			"맑음"
		]
	},
	"P 앨리스 페디": {
		"색상": [
			"yellow",
			"blue"
		],
		"분위기": [
			"데일리"
		],
		"디자인": [
			"체크",
			"풀컬러"
		],
		"날씨": [
			"맑음"
		]
	},
	"P 앰버 페디": {
		"색상": [
			"brown"
		],
		"분위기": [
			"시크"
		],
		"디자인": [
			"시럽"
		],
		"날씨": [
			"겨울"
		]
	},
	"P 어썸 페디": {
		"색상": [
			"white",
			"blue"
		],
		"분위기": [
			"화려",
			"시원"
		],
		"디자인": [
			"자개",
			"풀컬러"
		],
		"날씨": [
			"여름"
		]
	},
	"P 에뚜알 페디": {
		"색상": [
			"pink"
		],
		"분위기": [
			"화려",
			"청순"
		],
		"디자인": [
			"글리터",
			"풀컬러"
		],
		"날씨": [
			"봄",
			"맑음"
		]
	},
	"P 에이드 페디": {
		"색상": [
			"pink",
			"green"
		],
		"분위기": [
			"큐티"
		],
		"디자인": [
			"글리터",
			"풀컬러"
		],
		"날씨": [
			"여름",
			"맑음"
		]
	},
	"P 엘리자베스 페디": {
		"색상": [
			"pink"
		],
		"분위기": [
			"웨딩",
			"화려"
		],
		"디자인": [
			"글리터"
		],
		"날씨": [
			"맑음"
		]
	},
	"P 옐로우 스티치 페디": {
		"색상": [
			"yellow",
			"gray"
		],
		"분위기": [
			"데일리",
			"큐티"
		],
		"디자인": [
			"드로잉",
			"풀컬러"
		],
		"날씨": [
			"겨울"
		]
	},
	"P 오렌지 블라썸 페디": {
		"색상": [
			"orange"
		],
		"분위기": [
			"데일리",
			"큐티"
		],
		"디자인": [
			"그라데이션",
			"드로잉"
		],
		"날씨": [
			"가을",
			"맑음"
		]
	},
	"P 오로라 페디": {
		"색상": [
			"green",
			"blue"
		],
		"분위기": [
			"데일리"
		],
		"디자인": [
			"그라데이션",
			"시럽"
		],
		"날씨": [
			"여름"
		]
	},
	"P 오브 페디": {
		"색상": [
			"blue"
		],
		"분위기": [
			"시원",
			"활발"
		],
		"디자인": [
			"드로잉",
			"시럽"
		],
		"날씨": [
			"여름",
			"비"
		]
	},
	"P 오키드 페디": {
		"색상": [
			"purple"
		],
		"분위기": [
			"화려"
		],
		"디자인": [
			"자개",
			"시스루",
			"풀컬러"
		],
		"날씨": [
			"겨울"
		]
	},
	"P 올리버 페디": {
		"색상": [
			"white",
			"green"
		],
		"분위기": [
			"데일리"
		],
		"디자인": [
			"드로잉",
			"시럽"
		],
		"날씨": [
			"봄"
		]
	},
	"P 위티 페디": {
		"색상": [
			"purple",
			"white",
			"blue",
			"yellow"
		],
		"분위기": [
			"데일리",
			"큐티",
			"활발"
		],
		"디자인": [
			"드로잉",
			"시스루",
			"풀컬러"
		],
		"날씨": [
			"봄",
			"여름",
			"가을"
		]
	},
	"P 유니버스 페디": {
		"색상": [
			"black"
		],
		"분위기": [
			"화려"
		],
		"디자인": [
			"글리터",
			"풀컬러"
		],
		"날씨": [
			"봄",
			"여름",
			"가을",
			"겨울"
		]
	},
	"P 이리디센트 페디": {
		"색상": [
			"blue",
			"white"
		],
		"분위기": [
			"화려"
		],
		"디자인": [
			"매트",
			"풀컬러",
			"글리터"
		],
		"날씨": [
			"여름",
			"맑음"
		]
	},
	"P 이브닝 썬 페디": {
		"색상": [
			"red"
		],
		"분위기": [
			"청순",
			"데일리"
		],
		"디자인": [
			"자개",
			"시럽"
		],
		"날씨": [
			"봄",
			"가을",
			"맑음"
		]
	},
	"P 재즈 페디": {
		"색상": [
			"brown"
		],
		"분위기": [
			"시크",
			"데일리"
		],
		"디자인": [
			"드로잉",
			"시럽"
		],
		"날씨": [
			"가을"
		]
	},
	"P 잭팟 페디": {
		"색상": [
			"white",
			"yellow"
		],
		"분위기": [
			"데일리"
		],
		"디자인": [
			"풀컬러"
		],
		"날씨": [
			"여름",
			"맑음"
		]
	},
	"P 조이풀 페디": {
		"색상": [
			"red",
			"yellow",
			"blue"
		],
		"분위기": [
			"화려"
		],
		"디자인": [
			"풀컬러"
		],
		"날씨": [
			"봄",
			"여름",
			"가을",
			"겨울"
		]
	},
	"P 졸리 페디": {
		"색상": [
			"white",
			"green"
		],
		"분위기": [
			"데일리",
			"큐티"
		],
		"디자인": [
			"드로잉",
			"풀컬러"
		],
		"날씨": [
			"봄",
			"여름",
			"가을",
			"겨울"
		]
	},
	"P 쪽빛 페디": {
		"색상": [
			"blue"
		],
		"분위기": [
			"화려",
			"시원"
		],
		"디자인": [
			"드로잉",
			"글리터",
			"풀컬러"
		],
		"날씨": [
			"여름"
		]
	},
	"P 체리 베리 페디": {
		"색상": [
			"red"
		],
		"분위기": [
			"데일리",
			"큐티"
		],
		"디자인": [
			"드로잉",
			"시럽",
			"풀컬러"
		],
		"날씨": [
			"봄",
			"겨울"
		]
	},
	"P 체리퐁 페디": {
		"색상": [
			"white"
		],
		"분위기": [
			"데일리",
			"큐티"
		],
		"디자인": [
			"드로잉",
			"풀컬러"
		],
		"날씨": [
			"겨울"
		]
	},
	"P 체크메이트 페디": {
		"색상": [
			"white",
			"black"
		],
		"분위기": [
			"데일리",
			"시크"
		],
		"디자인": [
			"드로잉",
			"체크",
			"풀컬러"
		],
		"날씨": [
			"겨울"
		]
	},
	"P 체키 페디": {
		"색상": [
			"black",
			"purple"
		],
		"분위기": [
			"데일리"
		],
		"디자인": [
			"시스루",
			"드로잉",
			"풀컬러"
		],
		"날씨": [
			"겨울"
		]
	},
	"P 카니발 페디": {
		"색상": [
			"pink",
			"whilte",
			"red"
		],
		"분위기": [
			"화려"
		],
		"디자인": [
			"플컬러",
			"글리터"
		],
		"날씨": [
			"겨울",
			"눈"
		]
	},
	"P 카멜리아 페디": {
		"색상": [
			"pink",
			"whilte",
			"red"
		],
		"분위기": [
			"데일리",
			"큐티"
		],
		"디자인": [
			"드로잉",
			"풀컬러"
		],
		"날씨": [
			"봄",
			"맑음"
		]
	},
	"P 카프리 블루 페디": {
		"색상": [
			"blue"
		],
		"분위기": [
			"시원"
		],
		"디자인": [
			"매트",
			"시럽"
		],
		"날씨": [
			"여름"
		]
	},
	"P 칵테일 아워 페디": {
		"색상": [
			"pink"
		],
		"분위기": [
			"청순",
			"큐티"
		],
		"디자인": [
			"마블",
			"드로잉"
		],
		"날씨": [
			"봄",
			"맑음"
		]
	},
	"P 칸타빌레 페디": {
		"색상": [
			"blue"
		],
		"분위기": [
			"시원",
			"큐티"
		],
		"디자인": [
			"드로잉",
			"글리터"
		],
		"날씨": [
			"여름"
		]
	},
	"P 캐비어 페디": {
		"색상": [
			"black",
			"gray",
			"silver"
		],
		"분위기": [
			"화려",
			"시크"
		],
		"디자인": [
			"글리터",
			"풀컬러",
			"그라데이션"
		],
		"날씨": [
			"겨울"
		]
	},
	"P 캐쥬얼 페디": {
		"색상": [
			"green",
			"red"
		],
		"분위기": [
			"화려"
		],
		"디자인": [
			"풀컬러"
		],
		"날씨": [
			"겨울"
		]
	},
	"P 케미스트리 페디": {
		"색상": [
			"pink",
			"blue",
			"orange",
			"green",
			"purple"
		],
		"분위기": [
			"화려"
		],
		"디자인": [
			"매트",
			"그라데이션"
		],
		"날씨": [
			"봄"
		]
	},
	"P 코발트 블루 페디": {
		"색상": [
			"blue"
		],
		"분위기": [
			"시원"
		],
		"디자인": [
			"풀컬러"
		],
		"날씨": [
			"여름"
		]
	},
	"P 크러쉬 페디": {
		"색상": [
			"yellow",
			"blue"
		],
		"분위기": [
			"시원",
			"화려"
		],
		"디자인": [
			"풀컬러",
			"글리터"
		],
		"날씨": [
			"여름"
		]
	},
	"P 크런치 페디": {
		"색상": [
			"black"
		],
		"분위기": [
			"시크",
			"화려"
		],
		"디자인": [
			"자개",
			"풀컬러"
		],
		"날씨": [
			"겨울"
		]
	},
	"P 크레시다 페디": {
		"색상": [
			"green"
		],
		"분위기": [
			"시크"
		],
		"디자인": [
			"매트",
			"시럽"
		],
		"날씨": [
			"겨울"
		]
	},
	"P 크레용 페디": {
		"색상": [
			"red",
			"yellow",
			"green",
			"blue"
		],
		"분위기": [
			"큐티"
		],
		"디자인": [
			"풀컬러"
		],
		"날씨": [
			"가을"
		]
	},
	"P 클래시 페디": {
		"색상": [
			"green",
			"white",
			"gold"
		],
		"분위기": [
			"화려"
		],
		"디자인": [
			"시스루",
			"드로잉",
			"글리터",
			"풀컬러"
		],
		"날씨": [
			"겨울"
		]
	},
	"P 클래식 네이비 페디": {
		"색상": [
			"gold",
			"green"
		],
		"분위기": [
			"화려"
		],
		"디자인": [
			"글리터",
			"시럽"
		],
		"날씨": [
			"겨울"
		]
	},
	"P 클림트 페디": {
		"색상": [
			"white",
			"yellow"
		],
		"분위기": [
			"청순"
		],
		"디자인": [
			"풀컬러",
			"드로잉"
		],
		"날씨": [
			"겨울"
		]
	},
	"P 키윙 페디": {
		"색상": [
			"yellow"
		],
		"분위기": [
			"큐티"
		],
		"디자인": [
			"풀컬러",
			"드로잉"
		],
		"날씨": [
			"여름"
		]
	},
	"P 타이드 풀 페디": {
		"색상": [
			"white"
		],
		"분위기": [
			"시크"
		],
		"디자인": [
			"시럽",
			"드로잉"
		],
		"날씨": [
			"여름"
		]
	},
	"P 토끼의 봄 페디": {
		"색상": [
			"white",
			"blue",
			"yellow"
		],
		"분위기": [
			"큐티",
			"데일리"
		],
		"디자인": [
			"드로잉",
			"풀컬러"
		],
		"날씨": [
			"봄",
			"맑음"
		]
	},
	"P 트렌치 페디": {
		"색상": [
			"brown",
			"green"
		],
		"분위기": [
			"큐티",
			"데일리"
		],
		"디자인": [
			"시럽"
		],
		"날씨": [
			"가을"
		]
	},
	"P 틴트 버건디 페디": {
		"색상": [
			"red"
		],
		"분위기": [
			"시크",
			"데일리"
		],
		"디자인": [
			"시럽"
		],
		"날씨": [
			"가을",
			"겨울",
			"맑음"
		]
	},
	"P 틴트 블랙 페디": {
		"색상": [
			"gray"
		],
		"분위기": [
			"시크",
			"데일리"
		],
		"디자인": [
			"시럽"
		],
		"날씨": [
			"겨울",
			"맑음"
		]
	},
	"P 팅키윙키 페디": {
		"색상": [
			"white",
			"purple"
		],
		"분위기": [
			"큐티",
			"데일리"
		],
		"디자인": [
			"드로잉",
			"풀컬러"
		],
		"날씨": [
			"봄",
			"가을"
		]
	},
	"P 파이럿 페디": {
		"색상": [
			"black"
		],
		"분위기": [
			"화려"
		],
		"디자인": [
			"글리터"
		],
		"날씨": [
			"겨울",
			"눈"
		]
	},
	"P 파이어웍스 페디": {
		"색상": [
			"black",
			"red",
			"blue"
		],
		"분위기": [
			"화려"
		],
		"디자인": [
			"드로잉",
			"풀컬러"
		],
		"날씨": [
			"여름"
		]
	},
	"P 파티나 페디": {
		"색상": [
			"green"
		],
		"분위기": [
			"화려"
		],
		"디자인": [
			"자개",
			"풀컬러"
		],
		"날씨": [
			"여름"
		]
	},
	"P 파핑 캔디 페디": {
		"색상": [
			"white",
			"pink",
			"yellow",
			"blue"
		],
		"분위기": [
			"큐티"
		],
		"디자인": [
			"드로잉",
			"풀컬러"
		],
		"날씨": [
			"맑음"
		]
	},
	"P 판타지 페디": {
		"색상": [
			"pink"
		],
		"분위기": [
			"청순",
			"큐티"
		],
		"디자인": [
			"마블",
			"풀컬러"
		],
		"날씨": [
			"가을",
			"겨울"
		]
	},
	"P 팜 트리 페디": {
		"색상": [
			"green"
		],
		"분위기": [
			"시원",
			"화려"
		],
		"디자인": [
			"드로잉",
			"글리터"
		],
		"날씨": [
			"여름",
			"맑음"
		]
	},
	"P 팬시 페디": {
		"색상": [
			"red"
		],
		"분위기": [
			"데일리",
			"청순"
		],
		"디자인": [
			"마블",
			"풀컬러"
		],
		"날씨": [
			"가을"
		]
	},
	"P 팬지 페디": {
		"색상": [
			"blue",
			"pink"
		],
		"분위기": [
			"데일리",
			"시원"
		],
		"디자인": [
			"드로잉",
			"풀컬러"
		],
		"날씨": [
			"봄",
			"여름"
		]
	},
	"P 퍼시픽 페디": {
		"색상": [
			"white",
			"green"
		],
		"분위기": [
			"화려"
		],
		"디자인": [
			"드로잉"
		],
		"날씨": [
			"여름",
			"맑음"
		]
	},
	"P 퍼플 다이브 페디": {
		"색상": [
			"purple"
		],
		"분위기": [
			"화려"
		],
		"디자인": [
			"글리터",
			"풀컬러"
		],
		"날씨": [
			"겨울"
		]
	},
	"P 펑키코코 페디": {
		"색상": [
			"white",
			"black",
			"pink"
		],
		"분위기": [
			"데일리",
			"큐티"
		],
		"디자인": [
			"드로잉",
			"풀컬러"
		],
		"날씨": [
			"맑음"
		]
	},
	"P 페미닌노마드 1호 페디": {
		"색상": [
			"white",
			"pink",
			"gold"
		],
		"분위기": [
			"웨딩",
			"화려",
			"청순"
		],
		"디자인": [
			"드로잉"
		],
		"날씨": [
			"맑음"
		]
	},
	"P 페어리 페디": {
		"색상": [
			"purple",
			"pink"
		],
		"분위기": [
			"데일리",
			"청순"
		],
		"디자인": [
			"글리터",
			"시럽"
		],
		"날씨": [
			"맑음"
		]
	},
	"P 포지타노 페디": {
		"색상": [
			"blue"
		],
		"분위기": [
			"화려",
			"시원"
		],
		"디자인": [
			"자개",
			"글리터",
			"시럽"
		],
		"날씨": [
			"여름",
			"비"
		]
	},
	"P 포코 페디": {
		"색상": [
			"white",
			"blue",
			"red",
			"green"
		],
		"분위기": [
			"큐티"
		],
		"디자인": [
			"드로잉",
			"풀컬러"
		],
		"날씨": [
			"여름",
			"맑음"
		]
	},
	"P 폰드 페디": {
		"색상": [
			"green"
		],
		"분위기": [
			"화려",
			"시원"
		],
		"디자인": [
			"마블"
		],
		"날씨": [
			"여름"
		]
	},
	"P 프리즘 페디": {
		"색상": [
			"pink",
			"red"
		],
		"분위기": [
			"화려"
		],
		"디자인": [
			"자개",
			"시럽"
		],
		"날씨": [
			"가을"
		]
	},
	"P 프시케 페디": {
		"색상": [
			"purple"
		],
		"분위기": [
			"큐트",
			"데일리"
		],
		"디자인": [
			"매트",
			"드로잉",
			"그라데이션"
		],
		"날씨": [
			"봄",
			"맑음"
		]
	},
	"P 피오니 페디": {
		"색상": [
			"beige",
			"green"
		],
		"분위기": [
			"화려"
		],
		"디자인": [
			"풀컬러"
		],
		"날씨": [
			"겨울"
		]
	},
	"P 피치 크러쉬 페디": {
		"색상": [
			"pink",
			"red"
		],
		"분위기": [
			"화려",
			"시크"
		],
		"디자인": [
			"마블",
			"풀컬러"
		],
		"날씨": [
			"가을",
			"겨울",
			"맑음"
		]
	},
	"P 피콕 블루 페디": {
		"색상": [
			"blue"
		],
		"분위기": [
			"시원"
		],
		"디자인": [
			"풀컬러"
		],
		"날씨": [
			"여름"
		]
	},
	"P 피톤치드 페디": {
		"색상": [
			"blue",
			"green"
		],
		"분위기": [
			"시원"
		],
		"디자인": [
			"드로잉",
			"시럽"
		],
		"날씨": [
			"봄",
			"여름",
			"맑음"
		]
	},
	"P 핑크 솔트 페디": {
		"색상": [
			"pink"
		],
		"분위기": [
			"청순",
			"화려"
		],
		"디자인": [
			"글리터"
		],
		"날씨": [
			"봄",
			"맑음"
		]
	},
	"P 하바나 페디": {
		"색상": [
			"white"
		],
		"분위기": [
			"시원",
			"데일리"
		],
		"디자인": [
			"드로잉",
			"글리터",
			"풀컬러"
		],
		"날씨": [
			"여름",
			"맑음"
		]
	},
	"P 하와이안 후르츠 페디": {
		"색상": [
			"white",
			"yellow",
			"green"
		],
		"분위기": [
			"시원",
			"데일리"
		],
		"디자인": [
			"드로잉",
			"체크",
			"풀컬러"
		],
		"날씨": [
			"여름",
			"맑음"
		]
	},
	"P 하트비트 페디": {
		"색상": [
			"white",
			"pink"
		],
		"분위기": [
			"청순",
			"화려"
		],
		"디자인": [
			"글리터"
		],
		"날씨": [
			"봄",
			"겨울",
			"맑음"
		]
	},
	"P 헤이지 페디": {
		"색상": [
			"red"
		],
		"분위기": [
			"청순",
			"데일리"
		],
		"디자인": [
			"마블",
			"시럽"
		],
		"날씨": [
			"겨울"
		]
	},
	"P 홍매 페디": {
		"색상": [
			"red"
		],
		"분위기": [
			"청순",
			"데일리"
		],
		"디자인": [
			"드로잉",
			"풀컬러"
		],
		"날씨": [
			"봄"
		]
	},
	"P 딥 블루 씨 페디": {
		"색상": [
			"blue"
		],
		"분위기": [
			"시원",
			"화려"
		],
		"디자인": [
			"글리터"
		],
		"날씨": [
			"여름"
		]
	}
}